django_staticsite-1.1.0.dist-info/.DS_Store
django_staticsite-1.1.0.dist-info/DESCRIPTION.rst
django_staticsite-1.1.0.dist-info/entry_points.txt
django_staticsite-1.1.0.dist-info/LICENSE.txt
django_staticsite-1.1.0.dist-info/METADATA
django_staticsite-1.1.0.dist-info/metadata.json
django_staticsite-1.1.0.dist-info/RECORD
django_staticsite-1.1.0.dist-info/top_level.txt
django_staticsite-1.1.0.dist-info/WHEEL
staticsite/__init__.py
staticsite/models.py
staticsite/tests.py
staticsite/views.py
staticsite/management/__init__.py
staticsite/management/commands/__init__.py
staticsite/management/commands/buildstaticsite.py
