Metadata-Version: 2.0
Name: django-staticsite
Version: 1.1.0
Summary: Django static site generator for DEBUG and production.
Home-page: https://github.com/carltongibson/django-staticsite
Author: Carlton Gibson
Author-email: carlton.gibson@noumenal.es
License: BSD
Platform: UNKNOWN
